SDGDetector/SDGDetector.py
SDGDetector/__init__.py
sdgdetector-1.4.0.dist-info/licenses/LICENSE
sdgdetector-1.4.0.dist-info/METADATA
sdgdetector-1.4.0.dist-info/WHEEL
sdgdetector-1.4.0.dist-info/top_level.txt
sdgdetector-1.4.0.dist-info/RECORD
