Metadata-Version: 2.4
Name: SDGDetector
Version: 1.4.0
Summary: A library for classifying texts into one or more of the 17 SDGs using a pretrained transformer-based model or keyword extraction method, with an option to combine both approaches.
Home-page: https://gitlab.com/netmode/SDGDetector
Author: Ioanna Mandilara
Author-email: Ioanna Mandilara <ioanna_mandilara@yahoo.gr>
License: Creative Commons Attribution-NonCommercial 4.0 International (CC BY-NC 4.0) License
Project-URL: Homepage, https://gitlab.com/netmode/sdg-detector
Project-URL: Documentation, https://gitlab.com/netmode/sdg-detector/-/wikis/home
Classifier: Programming Language :: Python :: 3
Classifier: Operating System :: OS Independent
Requires-Python: >=3.11
License-File: LICENSE
Requires-Dist: numpy>=1.26.4
Requires-Dist: nltk>=3.9.1
Requires-Dist: sentence-transformers>=3.4.1
Requires-Dist: sentencepiece>=0.2.0
Requires-Dist: keras_preprocessing>=1.1.2
Dynamic: author
Dynamic: home-page
Dynamic: license-file
Dynamic: requires-python
